utils_psr1983/__init__.py
utils_psr1983/cloud_utils.py
utils_psr1983/git_utils.py
utils_psr1983-1.0.dist-info/METADATA
utils_psr1983-1.0.dist-info/WHEEL
utils_psr1983-1.0.dist-info/licenses/LICENSE
utils_psr1983-1.0.dist-info/RECORD
